convnd/convNd.py
convnd-0.1.0.dist-info/LICENSE
convnd-0.1.0.dist-info/METADATA
convnd-0.1.0.dist-info/WHEEL
convnd-0.1.0.dist-info/RECORD
